{"type": "article", "id": 12825, "title": "超模米兰达在Coach广告里带上了她的狗| 浮华日报", "description": "我们为你挑选了今天最重要和最好看的时尚新闻。", "date": "2015-07-30T14:05:40Z", "super_tag": "", "tags": [{"id": 13713, "name": "Raf Simon"}, {"id": 2034, "name": "Dior"}, {"id": 1782, "name": "Coach"}, {"id": 5170, "name": "Moncler"}, {"id": 3120, "name": "Levi's"}, {"id": 9725, "name": "Skechers"}, {"id": 13715, "name": "Altuzarra"}], "category": 19, "column": 8, "author": 113313, "comment_count": 7, "praise_count": 41, "image": "img/article/article_show/20160607140329qB4ucnvmKztxOfyC.jpg", "contents": "\n\n<h4>\r\n\t一些重要的新闻：\r\n</h4>\r\n<p>\r\n\t<a href=\"http://wwd.com/business-news/financial/dior-profits-rise-first-half-10194392/\" target=\"_blank\"><strong>Dior 上半年利润率上涨了 34%</strong></a><strong> </strong><strong>| </strong>Dior 发布财报，2015 年上半年财年营收 9.11 亿欧元，同比上升 22%，利润则达到 1.06 亿欧元，同比增长 34%  。Dior 表示其女装艺术总监 Raf Simon 的设计持续受到欢迎，以及皮具制品比如蕾哈娜代言的Diorama 手袋等都有良好表现。\r\n</p>\r\n<p>\r\n\t<span></span><a href=\"http://wwd.com/business-news/financial/moncler-profits-rise-10194566-10194566/\" target=\"_blank\"><strong>Moncler 净利润率和收益暴涨</strong></a><strong> </strong><span></span><strong>| </strong>美国和亚洲零售渠道的强劲推动力以及欧元贬值，令以奢侈羽绒制品闻名的 Moncler 上半年利润暴涨 88%，达到 3400 万欧元，营收增长 35%，至 2.95 亿欧元。CEO 表示，未来几个月内将优化供应链，并扩大产品品类。此前，Moncler 在 2013 年和 2014 年的盈利也一路上涨，并新增多家门店。\r\n</p>\r\n<p>\r\n\t<strong><a href=\"http://wwd.com/business-news/financial/skechers-stock-record-earnings-10194585/\" target=\"_blank\">虽然不够美，Skechers仍然卖得好</a> | </strong>第二季度，Skechers 净销售额超 8 亿美元，远超去年同期的 5.87 亿美元。刚一公布这个消息，Skechers 的股票上涨了 11% 至142 美元。CEO\r\nRobert Greenberg 表示大幅增长主要源于新产品上市和价格稍涨，大多数产品的销量如 Skechers\r\nGo 都有明显增幅。\r\n</p>\r\n<p>\r\n\t<a href=\"http://www.businesswire.com/news/home/20150729005536/en/Revlon-Reports-Quarter-2015-Results#.VbmKqvSl_4R\" target=\"_blank\"><strong>露华浓二季度净利润大涨但销售下滑</strong></a><strong> | </strong>露华浓 Revlon 公布二季度财报，二季度调整后净利润为 2900 万美元，同比上涨了 33%。而销售较去年同期下降 3.1% 至 4.824亿美元。\r\n</p>\r\n<h4>\r\n\t一些值得一看的：\r\n</h4>\r\n<p>\r\n\t<a href=\"http://www.businessinsider.com/you-can-now-buy-michael-jacksons-iconic-white-glove-2015-2\" target=\"_blank\">Michael Jackson 标志性的白手套将被拍卖</a>，起拍价两万美元。2009 年杰克逊去世几个月后，有另一双手套拍卖成交价为 35 万美金。\r\n</p>\r\n<p style=\"text-align:center;\">\r\n\t<img src=\"img/uploads/201606071403211wYnNoP3ekxREKpv.jpg\" title=\" \" alt=\" \" data-ratio=\"0.29074074\" data-format=\"jpeg\"> \r\n</p>\r\n<p>\r\n\t<a href=\"http://www.style.com/culture/art/2015/raf-simons-retrospective-032c\" target=\"_blank\">柏林有个 Raf simon 回顾展</a>。橱窗里摆放 Raf Simon (比利时设计师，现为 Dior 艺术总监)和老搭档摄影师 Willy\r\nVanderperre 20 年间在所有品牌的设计尝试，从贴纸到滑板，展现 “Youth as a practice” 概念。\r\n</p>\r\n<p style=\"text-align:center;\">\r\n\t<img src=\"img/uploads/20160607140322mr9FRkVziQXgO8b0.jpg\" title=\" \" alt=\" \" data-ratio=\"0.51151515\" data-format=\"jpeg\"> \r\n</p>\r\n<p style=\"text-align:center;\">\r\n\t<img src=\"img/uploads/20160607140322KjwPfexpE6Lhlt3v.jpg\" title=\" \" alt=\" \" data-ratio=\"0.66699219\" data-format=\"jpeg\"> \r\n</p>\r\n<p style=\"text-align:center;\">\r\n\t<img src=\"img/uploads/20160607140323gyQ5vqSjbF2UnhH6.jpg\" title=\" \" alt=\" \" data-ratio=\"0.66699219\" data-format=\"jpeg\"><span> </span> \r\n</p>\r\n<p>\r\n\t IT girl 最喜欢的品牌 <a href=\"http://www.whowhatwear.com/altuzarra-handbags-launch/\" target=\"_blank\">Altuzarra </a><a href=\"http://www.whowhatwear.com/altuzarra-handbags-launch/\" target=\"_blank\">也开始卖包了</a>，售价 2000－3000美元。\r\n</p>\r\n<p style=\"text-align:center;\">\r\n\t<img src=\"img/uploads/20160607140324uPCzKQ6yxBIDH4i5.jpg\" title=\" \" alt=\" \" data-ratio=\"0.56851852\" data-format=\"jpeg\"> \r\n</p>\r\n<p style=\"text-align:center;\">\r\n\t<img src=\"img/uploads/20160607140325j1kKuUd8mOXaRtMV.jpg\" title=\" \" alt=\" \" data-ratio=\"0.56851852\" data-format=\"jpeg\"><span> </span> \r\n</p>\r\n<span> </span> \r\n<p>\r\n\t巴黎品牌 <a href=\"http://www.whowhatwear.com/roger-vivier-caprices-julia-restoin-roitfeld/slide3\" target=\"_blank\">Roger Vivier 发布最新随想曲系列</a>，多彩又具有异域风情。 Roger Vivier是法式 IT girl 风格代表品牌，鞋履和手包在欧美大受欢迎。大表姐刘雯最近上节目也背过其红心包。\r\n</p>\r\n<p style=\"text-align:center;\">\r\n\t<img src=\"img/uploads/201606071403259OMs3pWvc4m71jYU.jpg\" title=\" \" alt=\" \" data-ratio=\"0.66574074\" data-format=\"jpeg\"> \r\n</p>\r\n<p style=\"text-align:center;\">\r\n\t<img src=\"img/uploads/20160607140326XMVU2ONm6RokI5Q8.jpg\" title=\" \" alt=\" \" data-ratio=\"0.68717949\" data-format=\"jpeg\"><span> </span> \r\n</p>\r\n<span> </span> \r\n<p>\r\n\t继 Lady Gaga 带着自己的法国斗牛犬入镜 Coach 的 “<a href=\"http://www.daozhou.net/a/20150703/25594.shtml\">COACH</a> PUPS” 广告大片后，<a href=\"http://www.fashiongonerogue.com/ariana-grande-miranda-kerr-coach-pup-campaign/\" target=\"_blank\">这一系列又新增了两位明星和其爱宠</a>，歌手 Ariana Grande 和超模 Miranda Kerr。同时 Coach 将向一些保护宠物的协会比如 Downtown Dog Rescue、No Kill Los Angeles 进行捐助。\r\n</p>\r\n<p style=\"text-align:center;\">\r\n\t<img src=\"img/uploads/20160607140326T3PViDOG8zSwQuyK.jpg\" title=\" \" alt=\" \" data-ratio=\"0.5\" data-format=\"jpeg\"><span> </span> \r\n</p>\r\n<p style=\"text-align:center;\">\r\n\t<em>Ariana Grande</em><em> 和她的狗狗</em> \r\n</p>\r\n<p style=\"text-align:center;\">\r\n\t<img src=\"img/uploads/20160607140327l6VWJbvymqOFHLjA.jpg\" title=\" \" alt=\" \" data-ratio=\"0.7125\" data-format=\"jpeg\"><span> </span> \r\n</p>\r\n<p style=\"text-align:center;\">\r\n\t<em>Miranda Kerr</em><em> 和她的狗狗</em> \r\n</p>\r\n<p>\r\n\t老搭档 <a href=\"http://hypebeast.com/2015/7/junya-watanabe-man-x-levis-2015-fall-winter-jackets\" target=\"_blank\">Levi's 和渡边淳弥（Junya Watanabe ）将再度合作</a>，设计 2015 秋冬系列的轻型夹克。\r\n</p>\r\n<p style=\"text-align:center;\">\r\n\t<img src=\"img/uploads/20160607140327GvbKe2gTjhIS0D9Z.jpg\" title=\" \" alt=\" \" data-ratio=\"0.52197802\" data-format=\"jpeg\"> \r\n</p>\r\n<p style=\"text-align:center;\">\r\n\t<img src=\"img/uploads/20160607140328nhockBpAYUuqGXTH.jpg\" title=\" \" alt=\" \" data-ratio=\"0.55462963\" data-format=\"jpeg\"><span> </span> \r\n</p>\r\n<span> </span> \r\n<h4>\r\n\t一些有意思的说法：\r\n</h4>\r\n<p>\r\n\t除了手链脚链项链，戴在腰上、胸前和<a href=\"http://www.marieclaire.com/fashion/news/a15165/leg-jewelry-trend/\" target=\"_blank\">腿部的链子</a>据说会再度流行（不要问我模特为什么长成这样）。\r\n</p>\r\n<p style=\"text-align:center;\">\r\n\t<img src=\"img/uploads/20160607140328beXfQ45wi2ZnMjA8.jpg\" title=\" \" alt=\" \" data-ratio=\"0.75\" data-format=\"jpeg\"> \r\n</p>\r\n<p style=\"text-align:center;\">\r\n\t<img src=\"img/uploads/20160607140329V03iTlcMn8sEXuG5.jpg\" title=\" \" alt=\" \" data-ratio=\"0.64136126\" data-format=\"jpeg\"> \r\n</p>\n\n\n"}