{"type": "article", "id": 14543, "title": "iPhone6 拍照手机壳", "description": "", "date": "2015-09-07T07:00:51Z", "super_tag": "", "tags": [], "category": 25, "column": 28, "author": 161922, "comment_count": 2, "praise_count": 38, "image": "img/article/article_show/201606060004278shMtwfVvB3gx6l2.jpg", "contents": "\n\n<p>\r\n\t来自台湾的 bitplay 团队继 SNAP!5 和 SNAP!6 之后推出新款拍照手机壳 SNAP! PRO ，专为 iphone6 定制。除了增加了拍照灵敏度之外，还设计了可替换的握把，在需要拍照时装上，以增强单手拍照的稳定性。此外，在握把的底部增加了脚架孔，可以安装通用的脚架，这样拍合照的时候就不用愁了。随着手机壳一起更新的还有超广角和全幅鱼眼两款镜头，算上之前的广角＋微距、鱼眼＋微距、三倍望远和偏光镜头，全面满足拍摄需要。手机壳有黑白两款，另有特质的胡桃木和硬枫木两种精装握把可选。产品目前已完成众筹，<a href=\"http://www.everydayobject.us/2015/09/03/bitplay-snap-pro/\" target=\"_blank\">这里是购买链接</a>。\r\n</p>\r\n<p style=\"text-align:center;\">\r\n\t<img src=\"img/uploads/20160726142026vMOfh1aKXZrc6JuW.jpg\" width=\"800\" height=\"533\" title=\" \" alt=\" \" data-ratio=\"0.66625\" data-format=\"jpeg\">\r\n</p>\r\n<p style=\"text-align:center;\">\r\n\t<img src=\"img/uploads/201607261420274cGLeJ6hoSw8RUVd.jpg\" width=\"1024\" height=\"768\" title=\" \" alt=\" \" data-ratio=\"0.75\" data-format=\"jpeg\">\r\n</p>\r\n<p style=\"text-align:center;\">\r\n\t<img src=\"img/uploads/20160726142028TKXLa0mOS3GQBDdv.jpg\" width=\"800\" height=\"533\" title=\" \" alt=\" \" data-ratio=\"0.66625\" data-format=\"jpeg\">\r\n</p>\r\n<p style=\"text-align:center;\">\r\n\t<img src=\"img/uploads/20160726142028bapeET9OnL2FtfUw.jpg\" width=\"680\" height=\"453\" title=\" \" alt=\" \" data-ratio=\"0.66617647\" data-format=\"jpeg\">\r\n</p>\n\n\n\n"}