{"type": "article", "id": 14713, "title": "这个设计了不起之今日最佳", "description": "我们尝试推荐一些最近发现的聪明设计。好设计并不只是一种装饰，它还是人们对于生活细节的各种思考，并且综合了包括技术、商业在内的多种力量。我们希望持续关注这些变化，它是美好生活的动力之一。", "date": "2015-09-10T08:05:34Z", "super_tag": "", "tags": [{"id": 15822, "name": "灯饰设计"}, {"id": 15823, "name": "&tradition"}, {"id": 15824, "name": "B&O"}, {"id": 15825, "name": "United Nude"}, {"id": 15826, "name": "Andy Bergmann"}, {"id": 15827, "name": "jaime hayon"}, {"id": 15828, "name": "Thierry Wille"}, {"id": 15829, "name": "Francis Bitonti"}, {"id": 15830, "name": "Marijana Dzambo"}], "category": 17, "author": 161922, "comment_count": 1, "praise_count": 25, "image": "img/article/article_show/20160607101948tjy8FhmLMKrzRBis.jpg", "contents": "\n\n<p>\r\n</p>\r\n<p>\r\n</p>\r\n<p>\r\n</p>\r\n<p>\r\n\t</p>\n<h3>\r\n\t\t‘formakami’  by  Jaime Hayon \r\n\t</h3>\r\n\r\n<p>\r\n</p>\r\n<p>\r\n</p>\r\n<p>\r\n</p>\r\n<p>\r\n\t西班牙艺术家 Jaime Hayon 和丹麦品牌 &amp;tradition 合作，呈现了一组非常素雅的白色灯笼系列。这组灯是用宣纸做的，象牙色的宣纸能使灯光非常明亮地透出来，轻盈而温暖。染黑了的橡木圈则帮助定形，也将纸灯分为上下两部分，下半部分成开口状，似乎模拟了灯笼下的吊穗，与传统的纸灯并不相同，也拥有一种现代艺术感。<a href=\"http://www.designboom.com/design/jaime-hayon-formakami-pendant-lamps-tradition-maison-et-objet-2015-09-08-2015/\" target=\"_blank\">点击这里可以查看更多信息。</a> \r\n</p>\r\n<p>\r\n</p>\r\n<p style=\"text-align:center;\">\r\n\t<img src=\"img/uploads/20160607101927oON4WnSx26JYekzC.jpg\" title=\" \" alt=\" \" data-ratio=\"0.66503667\" data-format=\"jpeg\"><span> </span> \r\n</p>\r\n<p style=\"text-align:center;\">\r\n\t<img src=\"img/uploads/20160607101927iR3b75QhArv9eCpx.jpg\" title=\" \" alt=\" \" data-ratio=\"1.4792176\" data-format=\"jpeg\"><span> </span> \r\n</p>\r\n<p style=\"text-align:center;\">\r\n\t<img src=\"img/uploads/20160607101928Pke3cnhH01SKAsDz.jpg\" title=\" \" alt=\" \" data-ratio=\"1.33374083\" data-format=\"jpeg\"><span> </span> \r\n</p>\r\n<p style=\"text-align:center;\">\r\n\t<img src=\"img/uploads/20160607101928VLeodOf6n1mjG48X.jpg\" title=\" \" alt=\" \" data-ratio=\"0.64547677\" data-format=\"jpeg\"><span> </span> \r\n</p>\r\n<p style=\"text-align:center;\">\r\n\t<img src=\"img/uploads/20160607101929TubNvdltkhWCZDmA.jpg\" title=\" \" alt=\" \" data-ratio=\"1.19559902\" data-format=\"jpeg\"> \r\n</p>\r\n<p>\r\n</p>\r\n<p>\r\n</p>\r\n<p>\r\n</p>\r\n<p>\r\n</p>\r\n<p>\r\n</p>\r\n<p>\r\n\t</p>\n<h3>\r\n\t\tThe SpoonStar by Andy Bergmann\r\n\t</h3>\r\n\r\n<p>\r\n</p>\r\n<p>\r\n</p>\r\n<p>\r\n</p>\r\n<p>\r\n</p>\r\n<p>\r\n\t这把星形的勺子来自美国有线电视新闻网（CNN）前任执行创意总监 Andy Bergmann ，这也是他第一次设计实物产品。四把勺子分别代表一汤匙、一茶匙、二分之一茶匙和四分之一茶匙，使用时，对应的一边充当手柄，非常方便。勺子的外形充满了童趣，也只有像 Andy Bergmann 这样的“外行”才能想到。这把勺子将在美国家居网站 Bed Bath &amp; Beyond 上售出，售价 6.99 美元，<a href=\"http://spoonstar.co/\" target=\"_blank\">这里是预购链接。</a> \r\n</p>\r\n<p>\r\n</p>\r\n<p style=\"text-align:center;\">\r\n\t<img src=\"img/uploads/20160607101929ycDaLz31XHjGM56K.jpg\" title=\" \" alt=\" \" data-ratio=\"0.664\" data-format=\"jpeg\"><span> </span> \r\n</p>\r\n<p style=\"text-align:center;\">\r\n</p>\r\n<p style=\"text-align:center;\">\r\n\t<img src=\"img/uploads/2016060710193083VoI7qO61dNJuvw.jpg\" title=\" \" alt=\" \" data-ratio=\"0.66533333\" data-format=\"jpeg\"> \r\n</p>\r\n<p>\r\n</p>\r\n<p style=\"text-align:center;\">\r\n\t<img src=\"img/uploads/20160607101930MkzRHcharUPf10Y4.jpg\" title=\" \" alt=\" \" data-ratio=\"0.66533333\" data-format=\"jpeg\"><span> </span> \r\n</p>\r\n<p style=\"text-align:center;\">\r\n\t<img src=\"img/uploads/201606071019308Anoa3Ek5exwc2u6.gif\" title=\" \" alt=\" \" data-ratio=\"0.69060773\" data-format=\"gif\"><span> </span> \r\n</p>\r\n<p style=\"text-align:center;\">\r\n\t<img src=\"img/uploads/20160607101936SoINHiwWgcqjprUE.jpg\" title=\" \" alt=\" \" data-ratio=\"0.608\" data-format=\"jpeg\"> \r\n</p>\r\n<p>\r\n</p>\r\n<p>\r\n</p>\r\n<p>\r\n</p>\r\n<p>\r\n</p>\r\n<p>\r\n</p>\r\n<p>\r\n\t</p>\n<h3>\r\n\t\tbeoplay A6 by Bang &amp; Olufsen(B&amp;O)\r\n\t</h3>\r\n\r\n<p>\r\n</p>\r\n<p>\r\n</p>\r\n<p>\r\n</p>\r\n<p>\r\n</p>\r\n<p>\r\n\t丹麦视听品牌 Bang &amp; Olufsen(B&amp;O) 发布最新无线音箱“ beoplay A6”。略有弯曲的外形像一片叶子，最大化放出声音。外面包裹着纯手工制造的 kvadrat 羊毛混纺面料，有很好的穿透力，也可以替换浅灰、深灰、黑玫瑰、藏青色等几种颜色，非常适合放在家里。使用时只需上下滑动，就可以调整音响的播放音量了。产品即将出售，<a href=\"http://www.bang-olufsen.com/zh\" target=\"_blank\">点击这里可以查看更多信息。</a> \r\n</p>\r\n<p>\r\n</p>\r\n<p style=\"text-align:center;\">\r\n\t<img src=\"img/uploads/20160607101937cw9Ys2SX7LlAtFW5.jpg\" title=\" \" alt=\" \" data-ratio=\"0.67359413\" data-format=\"jpeg\"><img src=\"img/uploads/20160607101937uDUeaV2C6WOgrtG7.jpg\" title=\" \" alt=\" \" data-ratio=\"0.62469438\" data-format=\"jpeg\"> \r\n</p>\r\n<p>\r\n</p>\r\n<p>\r\n</p>\r\n<p style=\"text-align:center;\">\r\n</p>\r\n<p style=\"text-align:center;\">\r\n\t<img src=\"img/uploads/201606071019371UQoIVO8uEjaMA2z.jpg\" title=\" \" alt=\" \" data-ratio=\"0.63202934\" data-format=\"jpeg\"><span> </span> \r\n</p>\r\n<p>\r\n\t<span> </span> \r\n</p>\r\n<p>\r\n</p>\r\n<p style=\"text-align:center;\">\r\n</p>\r\n<p style=\"text-align:center;\">\r\n\t<img src=\"img/uploads/20160607101938MCvAaT0BW3qUskDt.jpg\" title=\" \" alt=\" \" data-ratio=\"0.62469438\" data-format=\"jpeg\"> \r\n</p>\r\n<p>\r\n</p>\r\n<p style=\"text-align:center;\">\r\n\t<img src=\"img/uploads/20160607101938KdAF2lgzmpjo7wak.jpg\" title=\" \" alt=\" \" data-ratio=\"0.99877751\" data-format=\"jpeg\"> \r\n</p>\r\n<p>\r\n</p>\r\n<p>\r\n</p>\r\n<p style=\"text-align:center;\">\r\n\t<img src=\"img/uploads/20160607101939qskH7gi4lJNnfQpS.jpg\" title=\" \" alt=\" \" data-ratio=\"0.56356968\" data-format=\"jpeg\"><span> </span> \r\n</p>\r\n<p style=\"text-align:center;\">\r\n\t<img src=\"img/uploads/20160607101939QNGS8RmJwYHIftzo.jpg\" title=\" \" alt=\" \" data-ratio=\"1.15403423\" data-format=\"jpeg\"> \r\n</p>\r\n<p>\r\n</p>\r\n<p>\r\n</p>\r\n<p>\r\n</p>\r\n<p>\r\n</p>\r\n<p>\r\n</p>\r\n<p>\r\n\t</p>\n<h3>\r\n\t\ttabouret by Thierry Wille \r\n\t</h3>\r\n\r\n<p>\r\n</p>\r\n<p>\r\n</p>\r\n<p>\r\n</p>\r\n<p>\r\n</p>\r\n<p>\r\n\t比利时的设计师 Thierry Wille 重新定义了 “tabouret”（一种在 17 世纪法国很流行的无靠背矮凳），设计了这把颇有工业感的矮凳。凳子的四个腿使用了橡胶木，相互交叉，像四个翅膀。U 型座位好像将一块白色的板卷了起来，其实是采用 LG 豪美思(HI-MACS®)装饰用的人造大理石，使它更能长久使用。这把椅子搭配上不同的颜色，具有很强的装饰性。<a href=\"http://www.himacs.eu/en/taboustool\" target=\"_blank\">点击这里可以查看更多信息。</a> \r\n</p>\r\n<p>\r\n</p>\r\n<p style=\"text-align:center;\">\r\n\t<img src=\"img/uploads/20160607101940wiBOyVfx2cqZkIa9.jpg\" title=\" \" alt=\" \" data-ratio=\"0.665\" data-format=\"jpeg\"><span> </span> \r\n</p>\r\n<p style=\"text-align:center;\">\r\n\t<img src=\"img/uploads/20160607101940VDwFWZQhyiKB8HTY.jpg\" title=\" \" alt=\" \" data-ratio=\"0.665\" data-format=\"jpeg\"><span> </span> \r\n</p>\r\n<p style=\"text-align:center;\">\r\n\t<img src=\"img/uploads/20160607101941HU5oAG0fsyCXFmMb.jpg\" title=\" \" alt=\" \" data-ratio=\"0.665\" data-format=\"jpeg\"><span> </span> \r\n</p>\r\n<p style=\"text-align:center;\">\r\n\t<img src=\"img/uploads/20160607101941fJCwDX2ar83nLeYg.jpg\" title=\" \" alt=\" \" data-ratio=\"0.66481481\" data-format=\"jpeg\"><span> </span> \r\n</p>\r\n<p style=\"text-align:center;\">\r\n\t<img src=\"img/uploads/201606071019423mSJ7pMQo6D5exfz.jpg\" title=\" \" alt=\" \" data-ratio=\"0.66481481\" data-format=\"jpeg\"><span> </span> \r\n</p>\r\n<p style=\"text-align:center;\">\r\n</p>\r\n<p style=\"text-align:center;\">\r\n\t<img src=\"img/uploads/201606071019423IaytkhrDCzdRMm1.jpg\" title=\" \" alt=\" \" data-ratio=\"0.62962963\" data-format=\"jpeg\"> \r\n</p>\r\n<p>\r\n</p>\r\n<p>\r\n</p>\r\n<p>\r\n</p>\r\n<p>\r\n</p>\r\n<p>\r\n</p>\r\n<p>\r\n</p>\r\n<p>\r\n\t</p>\n<h3>\r\n\t\t3D 打印鞋跟 by Francis Bitonti\r\n\t</h3>\r\n\r\n<p>\r\n</p>\r\n<p>\r\n</p>\r\n<p>\r\n</p>\r\n<p>\r\n</p>\r\n<p>\r\n\t3D 打印技术的兴起帮助产品实现定制，也出现了越来越多的概念产品。美国设计师 Francis Bitonti 为荷兰品牌 United Nude 打造一系列的鞋，拥有金色的 3D 鞋跟。经过电脑的严密演算，得以做成如此夸张的造型。鞋面依然是黑色皮革，所以穿上与普通的鞋并无多少差别。这一系列产品正在 United Nude 旗舰店展出。\r\n</p>\r\n<p>\r\n</p>\r\n<p style=\"text-align:center;\">\r\n\t<img src=\"img/uploads/20160607101943ycoWpVJhGwFZ7HNA.jpg\" title=\" \" alt=\" \" data-ratio=\"0.97222222\" data-format=\"jpeg\"><span> </span> \r\n</p>\r\n<p>\r\n\t<span></span> \r\n</p>\r\n<p>\r\n</p>\r\n<p>\r\n</p>\r\n<p style=\"text-align:center;\">\r\n\t<img src=\"img/uploads/20160607101943ab3QX7dgMsJP9ukZ.jpg\" title=\" \" alt=\" \" data-ratio=\"0.80555556\" data-format=\"jpeg\"><span> </span> \r\n</p>\r\n<p style=\"text-align:center;\">\r\n</p>\r\n<p style=\"text-align:center;\">\r\n\t<img src=\"img/uploads/20160607101944lWRZ5k4Pp8zXGgAu.jpg\" title=\" \" alt=\" \" data-ratio=\"0.71428571\" data-format=\"jpeg\"> \r\n</p>\r\n<p>\r\n</p>\r\n<p style=\"text-align:center;\">\r\n\t<img src=\"img/uploads/20160607101944UkWftGi3SC0PFl7V.jpg\" title=\" \" alt=\" \" data-ratio=\"1.0\" data-format=\"jpeg\"> \r\n</p>\r\n<p>\r\n</p>\r\n<p>\r\n</p>\r\n<p>\r\n</p>\r\n<p>\r\n</p>\r\n<p>\r\n</p>\r\n<p>\r\n\t</p>\n<h3>\r\n\t\tJikka Basket by Marijana Dzambo\r\n\t</h3>\r\n\r\n<p>\r\n</p>\r\n<p>\r\n</p>\r\n<p>\r\n</p>\r\n<p>\r\n</p>\r\n<p>\r\n\t这是装面包的篮子，其实也可以做餐盘。黑色的卡纸折出像扇子一样的外形，放在圆形的木板上，像一个小型的雕塑，非常有质感。木板的中间事先空出一块卡住纸，再用一小块木头卡在其中稳定。将食物放在其中，这样打开时就很有惊喜之感。<a href=\"http://www.yankodesign.com/2015/09/08/dough-gazebo/\" target=\"_blank\">点击这里可以查看更多信息。</a> \r\n</p>\r\n<p>\r\n</p>\r\n<p style=\"text-align:center;\">\r\n\t<img src=\"img/uploads/201606071019458xjaCq5XlMJfsdhT.jpg\" title=\" \" alt=\" \" data-ratio=\"0.76095238\" data-format=\"jpeg\"><span> </span> \r\n</p>\r\n<p style=\"text-align:center;\">\r\n\t<img src=\"img/uploads/20160607101945HQvEdsJj78Nf4ymc.jpg\" title=\" \" alt=\" \" data-ratio=\"0.65904762\" data-format=\"jpeg\"><span> </span> \r\n</p>\r\n<p style=\"text-align:center;\">\r\n\t<img src=\"img/uploads/20160607101946a3OJqY0sHQGzutf9.jpg\" title=\" \" alt=\" \" data-ratio=\"0.65904762\" data-format=\"jpeg\"><span> </span> \r\n</p>\r\n<p style=\"text-align:center;\">\r\n\t<img src=\"img/uploads/201606071019464DASvf9P60jo8COL.jpg\" title=\" \" alt=\" \" data-ratio=\"0.76095238\" data-format=\"jpeg\"><span> </span> \r\n</p>\r\n<p style=\"text-align:center;\">\r\n\t<img src=\"img/uploads/201606071019472VqAedJECu7vHTBX.jpg\" title=\" \" alt=\" \" data-ratio=\"0.76095238\" data-format=\"jpeg\"> \r\n</p>\r\n<p>\r\n</p>\r\n<div>\r\n</div>\n\n\n\n"}