{"type": "article", "id": 16384, "title": "一向增长迅猛的中国市场，这次竟然拖了洲际的后腿", "description": "但在实施“轻资产”策略、持续抛售自有酒店资产后，洲际的表现好起来了", "date": "2015-10-21T15:03:11Z", "super_tag": "", "tags": [{"id": 667, "name": "酒店"}, {"id": 17561, "name": "IHG"}], "category": 18, "author": 2007, "comment_count": 2, "praise_count": 21, "image": "img/article/article_show/20160607102448xJz5K0FNyinTaqw2.jpg", "contents": "\n\n<p>\r\n\t国内的两大酒店集团锦江与铂涛完成“合体”后，他们依然没法被称作“全球最大的酒店集团”——至少在房间数上，还无法与洲际（IHG）、希尔顿、万豪这样的国际级酒店集团相比。\r\n</p>\r\n<p>\r\n\t10 月 20 日，洲际公布了<a href=\"http://www.ihgplc.com/index.asp?PageID=57&amp;NewsID=3528\" target=\"_blank\">集团的第三季度财报</a>。本季度，IHG 最看重的财报数据“每间可售房收入”（RevPAR，即客房实际总收入/客房总数）增长达到了 4.8%，超出分析师预期。\r\n</p>\r\n<p>\r\n\t在全球市场中，表现最好的是欧洲市场，RevPAR 增长达到了 7.8%。而一向表现不错的中国市场，虽然入驻率提升了，但在房价整体下跌的影响下，导致 RevPAR 这一指标反而跌了 0.7%。不过公司管理层表示，对中国区的发展仍有信心。\r\n</p>\r\n<p>\r\n\t早几年，洲际和其他的国际酒店集团一样，转向了抛售高价自有酒店资产、以“托管经营”或是“特许加盟”模式扩张的思路。今年 7 月，洲际就将其位于香港的旗舰资产“香港洲际酒店”对外出售，最终成交价格达到了 9.4 亿美元，远远超出了建筑本身 2.98 亿美元的估值。\r\n</p>\r\n<p>\r\n\t转型期能有如此表现，投资者也相当高兴。财报公布后，洲际在伦敦上市的公司股票在早盘一度出现了近 5% 的上涨。2014 年，洲际回馈给投资者的分红超过 10 亿美元。\r\n</p>\n\n\n"}