{"type": "article", "id": 17193, "title": "什么值得买，给你一份使用指南：smzdm", "description": null, "date": "1970-01-01T00:00:00Z", "super_tag": null, "tags": [], "category": null, "author": 998, "comment_count": 0, "praise_count": 1, "image": "img/default_images/missing_article.png", "contents": "\n\n<p>\r\n\t如果不知道该买什么，或是从哪开始逛起，什么值得买（<a href=\"http://itunes.apple.com/cn/app/shen-me-zhi-mai-dian-shang/id518213356?mt=8\" target=\"_blank\">iPhone</a><span> |</span><a href=\"http://www.wandoujia.com/apps/com.smzdm.client.android\" target=\"_blank\"> Android</a>）一向是折扣季人手必备的工具。\r\n</p>\r\n<p>\r\n\t<span>从 2011 年的黑色星期五开始，什么值得买的工作安排基本上就是跟着各个电商的大型时间节点走，从黑色星期五、双十一、双十二到 6·18 大促，它们都推出了相应的专题，实时放出优惠信息乃至是“神价格”。</span>\r\n</p>\r\n<p>\r\n\t现在，什么值得买的手机端已经打通了天猫的购买渠道，如果准备在双十一在天猫蹲点，其实看什么值得买编辑整理出来、实时更新的汇总频道，总比在天猫主场逛得头晕目眩要来得方便。\r\n</p>\r\n<p>\r\n</p>\r\n<p style=\"text-align:center;\">\r\n\t<img src=\"img/uploads/20160605202951Ysevg4cO0oknA58D.jpg\" title=\"什么值得买\" alt=\"什么值得买\" data-ratio=\"0.88518519\" data-format=\"jpeg\"><span><em>什么值得买</em></span>\r\n</p>\r\n<p>\r\n</p>\r\n<p>\r\n\t另外，在双 11 之前，什么值得买已经拿到了很多电商平台的值友专属优惠券，可以在什么值得买优惠券频道领用。其实不仅仅是双十一，平时什么值得买也会联合电商网站举办活动，比如目前仍在进行的日淘节，就是网易考拉、云猴全球购等跨境电商与什么值得买合作的。\r\n</p>\r\n<p>\r\n\t另外，在新版客户端里加入的订阅功能，会实时推送关注商品品类的最新的优惠价格。价格合适即可入手，不一定非得在那一天挤到头破血流。\r\n</p>\r\n<p>\r\n</p>\n\n\n"}