{"type": "article", "id": 18186, "title": "《金钱本色》", "description": null, "date": "1970-01-01T00:00:00Z", "super_tag": null, "tags": [], "category": null, "author": 102277, "comment_count": 0, "praise_count": 1, "image": "img/default_images/missing_article.png", "contents": "\n\n<h1>\r\n\t《金钱本色》（The Color of Money，1986）\r\n</h1>\r\n<p>\r\n</p>\r\n<p style=\"text-align:center;\">\r\n\t<img src=\"img/uploads/201606052042307xsOLtiR89PewbIu.jpg\" title=\" \" alt=\" \" data-ratio=\"0.75\" data-format=\"jpeg\"><span> </span> \r\n</p>\r\n<p>\r\n\t《金钱本色》是马丁·斯科塞斯对《江湖浪子》的致敬之作，不仅找来保罗·纽曼重新出演艾迪一角，同时也透过他精巧的剪接手法将影片的动能与刺激推上另一个高峰。虽然影片的情节是一趟从芝加哥出发前往大西洋城的「特训」，但实际上多数场景都是在芝加哥所拍摄，也呈现了风城破败的另一面（风城一名主要来自相邻的密西根湖总是送来阵阵狂风）。\r\n</p>\r\n<p>\r\n\t本片的芝加哥延续了《骗中骗》的烟雾袅绕的室内场景，但剥下了怀旧的气息；赌徒不再只是喝着酒、抽着雪茄，他们也在厕所里用鼻孔吸着古柯碱，让芝加哥宏伟面貌下的危险阴影逐渐从影片中渗透出来，影片主角文森甚至不愿意让女朋友待在其中一个撞球间里。虽然过了三十年，但影片当中许多的撞球间仍散落在城区四处，打开大门欢迎着酒鬼与骗徒，如三位主角第一次相遇的费兹杰罗（Fitzgerald’s）。\r\n</p>\r\n<p>\r\n\t另外一方面，影片也让更多的非裔美国人出演重要角色，呈现出这座伟大城市鲜为人知的另一面。从二十世纪初到二十世纪中，许多非裔美国人从南方迁移到芝加哥附近，尤其是在芝加哥南方靠近芝加哥大学的区域定居。《金钱本色》的剧情或许是趟公路之旅，但导演有意无意地以芝加哥的边缘地带建构了影片的空间，有些肮脏，但总有人能够受到幸运女神的青睐。\r\n</p>\r\n<p>\r\n</p>\r\n<div>\r\n</div>\n\n\n"}