{"type": "article", "id": 20521, "title": "你看得出来这个清新住宅，原来是100多年前的老公寓吗？", "description": "其他空间白净柔和如一张新画板，只待生活的色彩在上面铺张开来。\r\n", "date": "2016-01-11T13:29:40Z", "super_tag": "", "tags": [{"id": 14006, "name": "住宅设计"}, {"id": 435, "name": "室内设计"}, {"id": 15631, "name": "旧房改造"}], "category": 17, "author": 1329, "comment_count": 6, "praise_count": 190, "image": "img/article/article_show/201607021401247ZwTtmrFzQjapWyU.jpg", "contents": "\n\n<p>\r\n\t宽阔的空间，高度足够的天花板、丰富的自然光线，葡萄牙里斯本这幢建于 19 世纪末的旧式公寓 NANA 基本上具备了一座理想住宅所需的基础条件。但它太古旧了，既不能满足当代家庭生活的格局，部分陈年内饰也仿若再经不起住户的折腾。\r\n</p>\r\n<p>\r\n\t最近，来自里斯本当地的设计事务所 RAR 接手了 NANA 公寓的改造项目，设计的出发点着力于如何为建于 19 世纪末的住宅老楼，赋予符合当代审美的格调与当代生活功能空间。\r\n</p>\r\n<p>\r\n\t设计团队保留了 NANA 公寓部分原有的装饰元素，比如印满岁月痕迹的木地板与蓝色图案的陶瓷墙砖，<a href=\"http://www.dezeen.com/2016/01/09/rar-studio-19th-century-apartment-renovation-lisbon-portugal-marble-bathrooms/\" target=\"_blank\">在建筑师 Rita Aguiar Rodrigues 看来</a>，这是最能定义这幢公寓家的身份的元素。而改造思路也是循着空间原有的特征进行的。\r\n</p>\r\n<p>\r\n</p>\r\n<p style=\"text-align:center;\">\r\n\t<img src=\"img/uploads/20160702140118jxc1In8R7m5SQg0X.jpg\" width=\"936\" height=\"1079\" title=\"1\" alt=\"1\" data-ratio=\"1.15277778\" data-format=\"jpeg\"> \r\n</p>\r\n<p style=\"text-align:center;\">\r\n\t<img src=\"img/uploads/20160702140118VJUp7WdXow9345Th.jpg\" width=\"936\" height=\"1246\" title=\"厨房与餐厅\" alt=\"厨房与餐厅\" data-ratio=\"1.33119658\" data-format=\"jpeg\"><span>厨房与餐厅</span> \r\n</p>\r\n<p>\r\n</p>\r\n<p>\r\n\t墙面和家具以纯白色调为主，再加上大量涌入的自然光线，创造出极为通透的视觉体验，但却丝毫没有性冷淡风的感觉。\r\n</p>\r\n<p>\r\n</p>\r\n<p style=\"text-align:center;\">\r\n\t<img src=\"img/uploads/201607021401188CIvSJ1nGRkt2lxd.jpg\" width=\"1080\" height=\"771\" title=\"1\" alt=\"1\" data-ratio=\"0.71388889\" data-format=\"jpeg\"> \r\n</p>\r\n<p style=\"text-align:center;\">\r\n\t<img src=\"img/uploads/20160702140119pvWXPFaLrgGDeskH.jpg\" width=\"1080\" height=\"771\" title=\"1\" alt=\"1\" data-ratio=\"0.71388889\" data-format=\"jpeg\"> \r\n</p>\r\n<p style=\"text-align:center;\">\r\n\t<img src=\"img/uploads/20160702140120JVgmNlUMx35HtezF.jpg\" width=\"1080\" height=\"771\" title=\"起居室\" alt=\"起居室\" data-ratio=\"0.71388889\" data-format=\"jpeg\"><span>起居室</span> \r\n</p>\r\n<p style=\"text-align:center;\">\r\n\t<img src=\"img/uploads/20160702140120hom9PRSAF5CKLtWV.jpg\" width=\"1080\" height=\"771\" title=\"1\" alt=\"1\" data-ratio=\"0.71388889\" data-format=\"jpeg\"> \r\n</p>\r\n<p style=\"text-align:center;\">\r\n\t<img src=\"img/uploads/201607021401211cbQONYxnHedjTLX.jpg\" width=\"1080\" height=\"771\" title=\"卧室\" alt=\"卧室\" data-ratio=\"0.71388889\" data-format=\"jpeg\"><span>卧室</span> \r\n</p>\r\n<p>\r\n</p>\r\n<p>\r\n\t整个布局基本上是按照业主的需求而设，三处并排在卧室一侧的空间被设置为存储收纳系统，从地板到天花板的充足高度，基本上满足了全家的收纳需求。\r\n</p>\r\n<p>\r\n</p>\r\n<p style=\"text-align:center;\">\r\n\t<img src=\"img/uploads/20160702140121NK8Cu7v2WpQ9Alfc.jpg\" width=\"1080\" height=\"771\" title=\"1\" alt=\"1\" data-ratio=\"0.71388889\" data-format=\"jpeg\"> \r\n</p>\r\n<p style=\"text-align:center;\">\r\n\t<img src=\"img/uploads/20160702140122V2xUC1WKuLrPdXQf.jpg\" width=\"1080\" height=\"771\" title=\"存储收纳空间\" alt=\"存储收纳空间\" data-ratio=\"0.71388889\" data-format=\"jpeg\"><span>存储收纳空间</span> \r\n</p>\r\n<p>\r\n</p>\r\n<p>\r\n\t设计的重点放在了卫浴空间，也是整个公寓改造设计痕迹最多的地方。\r\n</p>\r\n<p>\r\n\t设计师从主卧室一侧为浴室设置了专门的进出通道，并采取错位布局的结构，以便于处理好内部干湿分离等问题。\r\n</p>\r\n<p>\r\n\t黑白单色与浅桃色的葡萄牙大理石材质的运用颇为抢眼，基本上覆盖了水槽和淋浴间的墙壁，辅以古旧木地板、白色墙壁与高处的天窗，形成了一个略带有女性温柔气质的空间，柔软而恬静。\r\n</p>\r\n<p>\r\n</p>\r\n<p style=\"text-align:center;\">\r\n\t<img src=\"img/uploads/20160702140122LvzyH4MYEx1ghpaQ.jpg\" width=\"1080\" height=\"772\" title=\"1\" alt=\"1\" data-ratio=\"0.71481481\" data-format=\"jpeg\"> \r\n</p>\r\n<p style=\"text-align:center;\">\r\n\t<img src=\"img/uploads/20160702140123qkKcVG9SI4W7hNBa.jpg\" width=\"1080\" height=\"1362\" title=\"浅桃色大理石质感卫生间\" alt=\"浅桃色大理石质感卫生间\" data-ratio=\"1.26111111\" data-format=\"jpeg\"><span>浅桃色大理石质感卫生间</span> \r\n</p>\r\n<p style=\"text-align:center;\">\r\n\t<img src=\"img/uploads/201607021401232Ti1BRwzHnZNqYUV.jpg\" width=\"936\" height=\"1146\" title=\"1\" alt=\"1\" data-ratio=\"1.22435897\" data-format=\"jpeg\"> \r\n</p>\r\n<p style=\"text-align:center;\">\r\n\t<img src=\"img/uploads/20160702140124qgNcC8rSDw0pHT7y.jpg\" width=\"1080\" height=\"771\" title=\"黑白色大理石质感浴室空间\" alt=\"黑白色大理石质感浴室空间\" data-ratio=\"0.71388889\" data-format=\"jpeg\"><span>黑白色大理石质感浴室空间</span> \r\n</p>\r\n<p>\r\n</p>\r\n<p>\r\n\t看上去这是一个内饰精简的公寓，鲜有冗余的装饰，但原木地板、白色墙壁与充足采光构建起来的空间，却给业主一家留下了软装多样化的可能性。\r\n</p>\r\n<p>\r\n\t图片来自 <a href=\"http://www.rar-studio.com/\" target=\"_blank\">RAR Studio</a> \r\n</p>\r\n<div>\r\n</div>\n\n"}