{"type": "article", "id": 24350, "title": "如果你是个温和朴实的旅店老板，印尼的这家青旅是个榜样", "description": "这家青旅算不上有多大特色，但它努力弥补当地气候上的缺陷并更多地促进租客的交流。\r\n", "date": "2016-03-24T07:00:10Z", "super_tag": "", "tags": [{"id": 21120, "name": "印度尼西亚"}, {"id": 9528, "name": "酒店设计"}, {"id": 21452, "name": "青年旅社"}, {"id": 25309, "name": "Andyrahman Architect"}], "category": 17, "author": 161922, "comment_count": 4, "praise_count": 200, "image": "img/article/article_show/20160702104659tQoBjdzEPgqC0WyM.jpeg", "contents": "\n\n<p class=\"\">          </p>\n<p>泗水（又称苏腊巴亚 Surabaya）是印度尼西亚的第二大城市，东爪哇省省会，拥有第二大海港和第二大机场朱安达国际机场。对不少游客来说，这里就是前往布罗莫腾格里塞梅鲁国家公园的中转站，如果停留上一天会发现，这里还有很多学校和工厂。</p>\n<p>挨着城中心 Airlangga University 不远的住宅区新建了一所小型青旅，主要客户就是读大学的学生和转机的游客。因为当地的热带雨林气候，平均气温有 23～31℃，修建时就重点考虑如何保障凉爽通风以及促进客人的沟通交流。</p>\n<p>房子有三层，一二层是住宿区，建筑的中间的天井打通了三层楼，下面放上了桌椅。镂空方格的水泥墙面是这里最显著的特征，出现在了天井、楼梯间和门口的外墙上，有借光通风的作用。仔细看会发现每一块被划分成 4 个小方块，它的空和实是随机的，反光颜色也有区别，表现出了轻盈感。</p>\n<div class=\"com-insert-images\"><figure style=\"margin:0;\">\r\n    <img src=\"img/uploads/20160702104652kWp25tUKdvY4MGSu.jpg\" alt=\"\" class=\"\" data-ratio=\"1.5015015\" data-format=\"jpeg\">\r\n</figure></div>\n<div class=\"com-insert-images\"><figure style=\"margin:0;\">\r\n    <img src=\"img/uploads/20160702104652JU4RMag3cwHZh6eB.jpg\" alt=\"\" data-ratio=\"0.66616541\" data-format=\"jpeg\">\r\n</figure></div>\n<div class=\"com-insert-images\">\n<figure class=\"\">\r\n    <img src=\"img/uploads/20160702104653SR4uE21Qi8hNFof9.jpg\" alt=\"\" data-ratio=\"1.49925037\" data-format=\"jpeg\">\r\n</figure><figure style=\"margin:0;\">\r\n    <img src=\"img/uploads/20160702104653XqGC8jxukw0MVvHW.jpg\" alt=\"\" data-ratio=\"0.75\" data-format=\"jpeg\">\r\n</figure>\n</div>\n<div class=\"com-insert-images\"><figure style=\"margin:0;\">\r\n    <img src=\"img/uploads/20160702104654kYz7GBOb61XxE4mJ.jpg\" alt=\"\" data-ratio=\"0.75277778\" data-format=\"jpeg\">\r\n</figure></div>\n<div class=\"com-insert-images\"></div>\n<div class=\"com-insert-images\"></div>\n<div class=\"com-insert-images\"><figure style=\"margin:0;\">\r\n    <img src=\"img/uploads/201607021046547ElQYT0nG4gb3qCV.jpg\" alt=\"\" data-ratio=\"0.75277778\" data-format=\"jpeg\">\r\n</figure></div>\n<p>在建筑上更重要的地方是一楼东边的一排卧室外面留出了 80 厘米的宽度，专门用来散热去潮，与中央天井一起构成了循环通风系统。</p>\n<div class=\"com-insert-images\"><figure style=\"margin:0;\">\r\n    <img src=\"img/uploads/201607021046558EcHgKsQwIlqFJW0.jpg\" alt=\"\" class=\"\" data-ratio=\"0.70740741\" data-format=\"jpeg\">\r\n</figure></div>\n<div class=\"com-insert-images\"><figure style=\"margin:0;\">\r\n    <img src=\"img/uploads/20160702104655dEFLDpXkaUmh6CT3.jpg\" alt=\"\" class=\"\" data-ratio=\"1.49925037\" data-format=\"jpeg\">\r\n<figcaption class=\"\"><div style=\"text-align: center;\">从建筑的右侧可以看到 80 厘米的通风道</div></figcaption></figure></div>\n<p>这家青旅其实只有 13 个单间，带来的收益并不高，所以在修建时也要将成本控制在低的范围里。水泥墙本身就是低成本的材料，镂空格就增加了活泼。而室内的家具也非常简单，使用了可回收材料，让房价更接近家庭。</p>\n<div class=\"com-insert-images\"><figure style=\"margin:0;\">\r\n    <img src=\"img/uploads/20160702104655RdAiGTjPzBDp8Xxq.jpg\" alt=\"\" data-ratio=\"0.75277778\" data-format=\"jpeg\">\r\n</figure></div>\n<p class=\"\">带开放式厨房的天井，可以将客人都聚集起来。这里是最具个性的地方，彩色条纹的金属桌椅、石子地面、红砖墙、水泥墙和不远处的木门木橱柜混搭在一起，本身也是多元的表达。</p>\n<div class=\"com-insert-images\"><figure style=\"margin:0;\">\r\n    <img src=\"img/uploads/20160702104656bnQxvB0jycIghdlP.jpg\" alt=\"\" data-ratio=\"0.66666667\" data-format=\"jpeg\">\r\n</figure></div>\n<p class=\"\">进门口的自行车停放点，在镂空墙的搭配下显得很酷。记得注意墙上有点扭曲的电表。</p>\n<div class=\"com-insert-images\"><figure style=\"margin:0;\">\r\n    <img src=\"img/uploads/2016070210465662lBRnI43dPyvLpk.jpg\" alt=\"\" data-ratio=\"0.66666667\" data-format=\"jpeg\">\r\n</figure></div>\n<div class=\"com-insert-images\"><figure style=\"margin:0;\">\r\n    <img src=\"img/uploads/20160702104657mMez9HBLfhn43D6w.jpg\" alt=\"\" data-ratio=\"0.75\" data-format=\"jpeg\">\r\n</figure></div>\n<div class=\"com-insert-images\"><figure style=\"margin:0;\">\r\n    <img src=\"img/uploads/20160702104658KFZ9wpHzEteD20Yc.jpg\" alt=\"\" data-ratio=\"0.66165414\" data-format=\"jpeg\">\r\n</figure></div>\n<p>青年旅社对穷游一族来说已不再陌生，我们也报道过很多有特色的青年旅舍，但仍有不少人抱怨住得并不舒服。而这家在建筑本身格局上很用心的青旅也许能提供一点参考。</p>\n<div class=\"com-insert-images\"><figure style=\"margin:0;\">\r\n    <img src=\"img/uploads/20160702104658rwuZelFdbjgvNnXy.jpg\" alt=\"\" class=\"\" data-ratio=\"1.41442716\" data-format=\"jpeg\">\r\n</figure></div>\n<div class=\"com-insert-images\">\n<figure style=\"margin:0;\">\r\n    <img src=\"img/uploads/201607021046589gXP1VNzER8JCZiW.jpg\" alt=\"\" data-ratio=\"1.41442716\" data-format=\"jpeg\">\r\n</figure><figure style=\"margin:0;\">\r\n    <img src=\"img/uploads/20160702104659sy1ZTLCzftwRHjcx.jpg\" alt=\"\" class=\"\" data-ratio=\"1.41442716\" data-format=\"jpeg\">\r\n</figure>\n</div>\n<p class=\"\">图片来自 <a href=\"http://www.archdaily.com/784043/bioclimatic-and-biophilic-boarding-house-andyrahman-architect\">archdaily</a>、<a href=\"http://www.andyrahmanarchitect.com/projects/?pageload=detpro&amp;idpro=89&amp;nf=Various\">andyrahmanarchitect</a></p>\n\n"}