{"type": "article", "id": 46862, "title": "分析师们很乐观，也许腾讯不会让《大逃杀》在中国被禁", "description": "也可能过于乐观了。", "date": "2017-11-03T23:27:40Z", "super_tag": "", "tags": [{"id": 29, "name": "Top 15"}, {"id": 43736, "name": "大逃杀"}, {"id": 43737, "name": "PUBG"}], "category": 54, "author": 798625, "comment_count": 91, "praise_count": 125, "image": "img/article/article_show/20171104003956nXyCvzehM2cPW5Ei.png", "contents": "<p finallycleanhtml=\"true\" nocleanhtml=\"true\">上周，一则关于大逃杀的消息不但令中国玩家疑虑丛生，也让全世界开始关注大逃杀在中国的命运。</p><p>10 月 27 日，<a href=\"http://tech.sina.com.cn/i/2017-10-27/doc-ifynfvar4519051.shtml\" rel=\"nofollow\">中国音像与数字出版协会游戏出版工作委员会发文称</a>，广电总局主管部门对于《绝地求生：大逃杀》类鼓励杀戮、单纯以杀死其他游戏玩家扮演的角色为手段实现最终目的的游戏明确持有否定态度。</p><p>总局认为，该类游戏普遍存在大量血腥暴力内容，其类似古罗马角斗场式的游戏体验与生存理念的设定，严重偏离社会主义核心价值观和中华民族传统文化习惯与道德规范，不利于青少年消费者的身心健康。因此委员会建议国内游戏企业不宜研发、引进此类游戏，它们也将难以获得出版运营许可。同时不提倡以测试此类游戏方式吸引用户，称电竞和直播平台也不宜对其宣传推广。</p><p>大逃杀的中国玩家已经占据了玩家整体的 40%，这让整个游戏界颇为关注这近半数的人口能否继续游戏。</p><p><a href=\"http://nikopartners.com/will-china-ban-playerunknowns-battlegrounds/\" rel=\"nofollow\">来自 Niko Partners 的分析师们预测</a>，中国不太会禁止这款游戏。他们给出的理由是，目前大逃杀在 Steam 国区售卖，其实是处于没有正式引进的“灰色地带”，但如果监管者想全面叫停游戏销售，就必须封锁整个平台。“要指出的是，Steam 在未来确实可能被封，但如今它还在运行。而且腾讯在运营着 Steam 的竞争平台 WeGame，任何法规的改变其实也都会影响到腾讯。”</p><p>腾讯已经收购了开发商 Bluehole 5% 的股份，如果 Bluehole 想在中国取得游戏的正式出版运营许可，不出意外必与腾讯这个本地伙伴合作，以对游戏做出调整迎合相关法令。就像当年 CS: GO 进入中国一样，当时完美世界对游戏进行了本地化的“和谐”，比如将血液由红变黑。</p><p>除了腾讯已几乎成为其在华命运共同体外，搭上大逃杀品类顺风车的厂商还有很多，所有人都在推出自家的大逃杀模式和手游（腾讯、小米、Snail Games 等）。</p><p>“广电不太可能完全将之禁止。尤其是有不少其他类似的射击游戏都存在了很多年。我们相信广电会对给予它们运营许可更加严格，确保其遵守法规，所以一些暴力效果更’假’的游戏会好过一点，比如《堡垒之夜》。”</p><p>但是仔细想想，上述任何一点理由都是站不住脚的。中国的环境可能比他们想象的更加任性，没有什么是不可能的。</p>"}