{"type": "article", "id": 63642, "title": "迪士尼加大视频流媒体投入，这一季度相关部门亏损翻倍", "description": "影业收入也下降了 15%。", "date": "2019-05-10T01:58:09Z", "super_tag": "", "tags": [{"id": 111, "name": "迪士尼"}, {"id": 4652, "name": "Hulu"}], "category": 18, "author": 1240135, "comment_count": 6, "praise_count": 27, "image": "img/article/article_show/20190509162614yBlQpMHi2atDT896.jpg", "contents": "<p finallycleanhtml=\"true\" nocleanhtml=\"true\">迪士尼发布了 2019 年第二季度财报，整体营收和利润均高于市场预期，但对流媒体视频的大幅投入也导致相关业务成本成倍增加。 </p><p>在这一季度中，计入了一笔来自早期收购 Hulu 股权重估中获得的约 50 亿美元收益后，迪士尼营收较上一年同期增长了 3% 至 149 亿美元，高于分析师预期的 145 亿美元，净利润较上一年同期增长了 85% 至 54 亿美元，高于分析师预期的 24 亿美元。</p><p>主题乐园和度假区相关业务是迪士尼的主要收入来源，这一季度营收较去年同期增长 5% 至 62 亿美元。这部分业务收入的增长主要得益于美国本土市场和邮轮业务的良好表现。上海迪士尼乐园购票率较低，但平均票价的上涨抵消了这部分不利影响，整体收入较去年同期仍有所增加。 </p><p>为了与 Netflix 竞争，迪士尼在去年 3 月成立了一个名为直接面向消费者和国际市场的新部门（DCTI ）。 ESPN+、Disney+、Hulu 等流媒体视频相关业务都被整合在这个新部门里。这一季度该部门营收较去年同期增长了 15% 至 10 亿美元，但在原创内容和整合 Hulu 中的大量投入，也让这个部门的亏损较上一年同期增长了一倍多至 4 亿美元。 </p><p>这一季度原创视频内容的投入主要集中在“歌舞青春”和星球大战中“曼达洛人”系列剧集制作上。财报中提到《复仇者联盟 4》将于 12 月在 Disney+ 上线，预示着 Disney+ 的上线时间可能会由最初宣布的 11 月推迟至 12 月。 </p><p>今年 3 月，迪士尼在完成对 21 世纪福克斯的收购后，所持有 Hulu 的股份增加至近 70%，并准备购买剩下的约 30% 股份，目前已经在和康卡斯特进行相关谈判。 </p><p>由于这一季度中《惊奇队长》和《小飞象》两部电影票房表现，不如去年同期的两部电影《黑豹》和《星球大战：最后的绝地武士》，迪士尼影业营收下降 15% 至 21 亿美元。 </p><p>接下来的 7 个月内迪士尼将有包括《星球大战 9：天行者的崛起》、《玩具总动员4》、《狮子王》、《冰雪奇缘 2 》等 15 部电影上映。分析师预测，真人版《狮子王》将成为今年票房收入最高的电影之一。</p><p>题图：<a href=\"https://unsplash.com/photos/RA7_Yz2pKDI?utm_source=unsplash&amp;utm_medium=referral&amp;utm_content=creditCopyText\" rel=\"nofollow\">Skylar Sahakian</a> on <a href=\"https://unsplash.com/search/photos/disney?utm_source=unsplash&amp;utm_medium=referral&amp;utm_content=creditCopyText\" rel=\"nofollow\">Unsplash</a></p>"}