{"type": "comment", "id": 605402, "parent_type": "comment", "parent_id": 605124, "date": "2018-01-11T15:47:38Z", "author": 826032, "comment_count": 1, "praise_count": 2, "contents": "1、你评论阳春白雪，下里巴人，质量和可看性的时候，那些奥斯卡得奖片不得哭死，票房不及爆米花片的1%。有些还得在艺术院线放才能存活。\n2、人家开片酬显然是看票房号召力的。貌似你比那些大片厂的老板制片人更了解哪些演员更值钱。这本身就是一种商业行为，所有都是商业运作产生的。就算是投资方在实拍阶段只给你“威廉姆斯”每天80美元薪酬，你可以不演啊，没人逼着你签合同演吧。再说了人现在只是贴出来补拍阶段的这些人的酬劳，而且这酬劳是马克自己跟制片方争取的。威廉姆斯不争取怪谁？（有些人说马克吃相难看，呵呵，商业行为有什么好说的，每个人都有档期，过来给你补拍另一边违约了损失谁陪？）真正实拍阶段双方片酬差多少大家都不清楚，这篇作者就跳出来大声疾呼“0.1%”，男女性别不平等是有的，但是你这种争取方式吗？\n3、再说了我还真特么就不信了，双方都有奥奖提名，难道你就因为马克的提名数少而作出前者比后者“ 银幕价值”高？"}