{"type": "comment", "id": 971819, "parent_type": "comment", "parent_id": 960049, "date": "2019-05-09T01:40:23Z", "author": 177752, "comment_count": 0, "praise_count": 1, "contents": "1.ps4与ps5存在过渡期是肯定的，就像当年ps2与ps3一样情况，但是最终，随着索尼停止ps4的服务以及ps5的装机量与各项服务的完善，ps4的用户也会过渡到ps5，就像xp与win7的关系一样。 2.不排除就是有个别玩家死守ps4但是，假设ps5真如索尼所说的有如此强大的硬件性能和画面表现，我觉得大部分人都乐意转向ps5的。 3.作为游戏开放商，更好的硬件支持也更利于做出新的游玩体验，尤其像r星这样的开发商，最近的大表哥2已经是本世代主机开放世界的天花板了，要想有突破，硬件性能的提升是必须的。 4.事实上，ps4已经走过10个年头了，不只是开发商，玩家当中也已经出现对其硬件性能跟不上的诟病声音（而且事实上ps4性能确实不行了）。索尼为什么要透漏ps5的信息？一方面是时机成熟，另一方面就是玩家对于ps5的呼声已经越来越高。"}