{"type": "comment", "id": 763029, "parent_type": "comment", "parent_id": 761849, "date": "2018-06-18T04:44:09Z", "author": 871894, "comment_count": 1, "praise_count": 0, "contents": "你需要考虑一个情况，县城的生源基本来自周边乡镇，很多人初高中都是寄宿制，一般一个星期回一次，我情况更特殊，高中在另外一个县，寒暑假才会回去。因此家里的电脑基本用不了，用的手机也没法上网，与网络的联系只有网吧，但去网吧就是为了玩而已。这也算是硬件条件限制。不过时代在前进，我高中毕业那年大屏安卓正好渗透进县城，现在的学生确实有着更多了解世界的可能性。\n另外保持好奇心是一个很个人和宽泛的思路，而这里并不是我个人的求助帖。但是讨论更普适的解决方案的话，我还没这个能力。我并非相关专业出身，只是根据自身经历回复而已，而经历的特殊性使其只具有参考价值，其中或许有共性，但我也没做过相关社会调查，空口无凭。\n所以回到我之前回复的本意，是我认为，即使同一经济水平，不同发展度的城市居民的思维差异仍然存在，决定行为的并不仅仅是经济，你所说的“那是真的穷”这一点并不成立，仅此而已。\n在这里也回复一下我对你后一句话的看法，我理解的从众心理是你有不一样的想法，但在考虑了标新立异的坏处后，选择随大流。当眼前只有一种选择，那就是随大流的时候，这并非从众，而是无奈，没有别的办法了。当然办法总是有的，但这就需要一个人具有获取各方面信息和独立判断的能力。我认为这应该是教育的目的之一，然而这是应试教育所不需要的。"}