{"type": "comment", "id": 396318, "parent_type": "comment", "parent_id": 394269, "date": "2017-03-09T13:33:22Z", "author": 854132, "comment_count": 1, "praise_count": 0, "contents": "你说的买方需求......汉化版改良版山寨版什么的有点无稽之谈了，现在PS4平台上大部分游戏有中文版，也不存在什么改良版更没有山寨版，而且大部分情况下，老的电玩人商家都不会和玩家产生什么纠纷，毕竟PS游戏碟都是真货嘛。比如你买一盘《战地1》，卖家不可能给你发《使命召唤》，也就不可能产生什么纠纷。毕竟主机游戏产业这块有它自己的一套条条框框。电玩商家大部分都会做中古这块生意，这也是大家全部认可的。平井一夫甚至到访过北京一家很小的电玩店，称他为索尼做出了自己的贡献。平井一夫也没授权那个电玩商家啊，对吧。虽然可以理解为作秀行为，但你说的什么授权之类的，在主机游戏产业这块真的不是这么回事。现在所有的主机是不锁区的，不锁区......也就是说我国行的机子可以玩欧美，港版的机子也可以玩国行，就是这样。对于卖家、买家、厂商、政府而言，是一个四赢局面。要不然政府也不会解禁了封禁长达十多年之久的主机游戏了。当下咱们政府要做的就是分级制度，把游戏产业做大。目前很多国内厂商也开始涉足PS4平台了"}