{"id": 1882, "genre": 1001, "title": "你最近都见识了哪些粉饰过的“礼貌”？", "description": "就是一种委婉的表达，你可别当真啊！（题图来自：Flickr）", "record_count": 4848, "comment_count": 0, "praise_count": 0, "image": "img/paper/paper_show/20170830101927eIjNoZGknYJtM4Ww.jpg", "page_style": 0, "category": 2, "column": 2, "type": "paper", "date": "2017-09-01T03:00:16Z", "options": [{"id": 233216, "content": "改天请你吃大餐", "image": null, "praise_count": 3, "perfect": 0, "select": 0, "author": 1121018}, {"id": 233472, "content": "稍后我联系你", "image": null, "praise_count": 2, "perfect": 0, "select": 0, "author": 1089204}, {"id": 233217, "content": "无可奉告", "image": null, "praise_count": 12, "perfect": 0, "select": 0, "author": 1012749}, {"id": 233473, "content": "不好吧……", "image": null, "praise_count": 2, "perfect": 0, "select": 0, "author": 1120657}, {"id": 233729, "content": "没事，没关系的", "image": null, "praise_count": 2, "perfect": 0, "select": 0, "author": 96183}, {"id": 233218, "content": "有空聚聚", "image": null, "praise_count": 9, "perfect": 0, "select": 0, "author": 1119989}, {"id": 233474, "content": "客气客气", "image": null, "praise_count": 1, "perfect": 0, "select": 0, "author": 1050868}, {"id": 233220, "content": "留下吃点饭吧！\n留下吃点饭吧！\n留下吃点饭吧！\n留下吃点饭吧！\n留下吃点饭吧！\n留下吃点饭吧！\n留下吃点饭吧！\n留下吃点饭吧！\n哈哈哈！！", "image": null, "praise_count": 10, "perfect": 0, "select": 0, "author": 1116223}, {"id": 233476, "content": "这钱我不能收，这真不能收……", "image": null, "praise_count": 7, "perfect": 0, "select": 0, "author": 997983}, {"id": 233221, "content": "要不你先来？你先吃？你先玩？你先用？", "image": null, "praise_count": 24, "perfect": 0, "select": 0, "author": 1117858}, {"id": 233477, "content": "狗粉丝有多远滚多远谢谢，你又是哪家媒体的拿出点好的作品好的创业公司出来秀秀啊？什么都拿不出来你叫什么啊？", "image": null, "praise_count": 1, "perfect": 0, "select": 0, "author": 1045799}, {"id": 233222, "content": "taylor用歌用mv骂人也不是一天两天了，不过这和题目有什么关系？题目是“粉饰的礼貌”，人也没粉饰啊，人是直接怼啊。在这一点上她是比你这个躲在背后粉饰性抹黑别人还把自己出的题目答到离题的来的好很多。", "image": null, "praise_count": 74, "perfect": 0, "select": 0, "author": 775918}, {"id": 233734, "content": "哈哈哈哈\n", "image": null, "praise_count": 0, "perfect": 0, "select": 0, "author": 1084187}, {"id": 233223, "content": "有空来玩呀", "image": null, "praise_count": 10, "perfect": 0, "select": 0, "author": 949271}, {"id": 233224, "content": "666", "image": null, "praise_count": 1, "perfect": 0, "select": 0, "author": 949271}, {"id": 233480, "content": "等一下，我先接个电话", "image": null, "praise_count": 3, "perfect": 0, "select": 0, "author": 1077939}, {"id": 233225, "content": "谢谢你，我们再转转", "image": "img/option/option/20170901124242whNgyWEumekDpU4q", "praise_count": 23, "perfect": 0, "select": 0, "author": 1121412}, {"id": 233481, "content": "下次请你吃饭", "image": null, "praise_count": 1, "perfect": 0, "select": 0, "author": 1122259}, {"id": 234505, "content": "服装店：我“这号码太小我穿不了”，店员：“你一点也不胖！”", "image": null, "praise_count": 1, "perfect": 0, "select": 0, "author": 956251}, {"id": 233226, "content": "我有喜欢的人了", "image": null, "praise_count": 10, "perfect": 0, "select": 0, "author": 1121414}, {"id": 233482, "content": "来就来吧，还带什么礼物啊", "image": null, "praise_count": 3, "perfect": 0, "select": 0, "author": 786195}, {"id": 233227, "content": "可以可以", "image": null, "praise_count": 14, "perfect": 0, "select": 0, "author": 1121415}, {"id": 233228, "content": "改天约", "image": null, "praise_count": 3, "perfect": 0, "select": 0, "author": 1121415}, {"id": 233484, "content": "一个人习惯了，感觉不需要依靠", "image": null, "praise_count": 4, "perfect": 0, "select": 0, "author": 1119953}, {"id": 234764, "content": "下次一起玩/改天吃个饭", "image": null, "praise_count": 0, "perfect": 0, "select": 0, "author": 1129827}, {"id": 233229, "content": "男足赢了！！！", "image": null, "praise_count": 2, "perfect": 0, "select": 0, "author": 1120445}, {"id": 233485, "content": "有时间请你吃饭", "image": null, "praise_count": 0, "perfect": 0, "select": 0, "author": 1075647}, {"id": 233231, "content": "去别人家有些事儿，走的时候，对方说:“再坐一会儿吧。”或者“留下来吃饭吧。”", "image": null, "praise_count": 72, "perfect": 0, "select": 0, "author": 1121421}, {"id": 233232, "content": "真的没关系～", "image": null, "praise_count": 4, "perfect": 0, "select": 0, "author": 837558}, {"id": 233488, "content": "同学说下次我请你吃，不存在的", "image": null, "praise_count": 3, "perfect": 0, "select": 0, "author": 1097384}, {"id": 233489, "content": "有时间我们再联系", "image": null, "praise_count": 0, "perfect": 0, "select": 0, "author": 1097424}, {"id": 233234, "content": "刚吃饱", "image": null, "praise_count": 2, "perfect": 0, "select": 0, "author": 1111687}, {"id": 233490, "content": "今天好美啊", "image": null, "praise_count": 0, "perfect": 0, "select": 0, "author": 1062311}, {"id": 233491, "content": "我喜欢你，不过我今天喝多了，明天早上就忘了。", "image": null, "praise_count": 6, "perfect": 0, "select": 0, "author": 1122341}, {"id": 233747, "content": "有空一起聚聚", "image": null, "praise_count": 2, "perfect": 0, "select": 0, "author": 1124173}, {"id": 233492, "content": "你真棒", "image": null, "praise_count": 2, "perfect": 0, "select": 0, "author": 1122347}, {"id": 233237, "content": "叔叔，我真的不要红包！！", "image": null, "praise_count": 57, "perfect": 0, "select": 0, "author": 1092823}, {"id": 233493, "content": "你是个好人，但是……", "image": null, "praise_count": 0, "perfect": 0, "select": 0, "author": 118986}, {"id": 233238, "content": "你今天真漂亮", "image": null, "praise_count": 5, "perfect": 0, "select": 0, "author": 1120913}, {"id": 233494, "content": "我不饿", "image": null, "praise_count": 2, "perfect": 0, "select": 0, "author": 1116180}, {"id": 233750, "content": "没事没事", "image": null, "praise_count": 0, "perfect": 0, "select": 0, "author": 842574}, {"id": 232471, "content": "明星表面不在乎别人的抹黑，声称用作品说话，用作品说话的方式是拍了超豪华mv在作品里骂人", "image": null, "praise_count": 546, "perfect": 0, "select": 0, "author": 688713}, {"id": 233239, "content": "得闲饮茶", "image": null, "praise_count": 21, "perfect": 0, "select": 0, "author": 1117745}, {"id": 233495, "content": "应该哒！", "image": null, "praise_count": 0, "perfect": 0, "select": 0, "author": 779602}, {"id": 234775, "content": "加个微信吧.", "image": null, "praise_count": 1, "perfect": 0, "select": 0, "author": 136629}, {"id": 232472, "content": "成分党美妆博主，呼吁粉丝理性消费，其实是说\"请大家认准我稍后将推出的品牌。\"", "image": null, "praise_count": 131, "perfect": 0, "select": 0, "author": 688713}, {"id": 233240, "content": "去洗澡了", "image": null, "praise_count": 9, "perfect": 0, "select": 0, "author": 1121433}, {"id": 233752, "content": "看了你的简历介绍 觉得挺不错的，稍后会通知你的          PS ：没下文了", "image": null, "praise_count": 0, "perfect": 0, "select": 0, "author": 1124259}, {"id": 233497, "content": "你说得对", "image": null, "praise_count": 0, "perfect": 0, "select": 0, "author": 1122372}, {"id": 233498, "content": "6666666（不知道你有没有觉得我在尬聊）", "image": null, "praise_count": 1, "perfect": 0, "select": 0, "author": 522195}]}