{"id": 2463, "genre": 1000, "title": "你最近一次取关某个社交媒体账号的原因是什么？", "description": "关注的理由千千万，但是取关的理由有时只要一个。（题图来自：iStock © Guzaliia Filimonova ）", "record_count": 18124, "comment_count": 44, "praise_count": 0, "image": "img/paper/paper_show/20180714172824whr8QnX731HFVBLK.jpg", "page_style": 0, "category": 1, "column": 2, "type": "paper", "date": "2018-07-16T17:00:00Z", "questions": [{"id": 4510, "title": "你最近一次取关某个社交媒体账号的原因是什么？", "content": "你最近一次取关某个社交媒体账号的原因是什么？", "genre": 2, "options": [{"id": 292620, "content": "支付时自动关注的服务号，居然发推送刷存在感", "image": "img/option/option/20180714175353J4mqesuWSZwILnhd.gif", "praise_count": 0, "perfect": 0, "select": 0}, {"id": 292621, "content": "说了自己不认同的话", "image": "img/option/option/20180714175442ECZgj2YkwalT35Ix.gif", "praise_count": 0, "perfect": 0, "select": 0}, {"id": 292622, "content": "博主被发现可能洗稿/抄袭", "image": "img/option/option/201807141756002PacNOVhsKuWCo9E.gif", "praise_count": 0, "perfect": 0, "select": 0}, {"id": 292623, "content": "“震惊体”，标题党，“XXX必转”", "image": "img/option/option/20180714175646V68Fv2NxjWqKan3J.gif", "praise_count": 0, "perfect": 0, "select": 0}, {"id": 292624, "content": "广告太多/辣眼睛", "image": "img/option/option/20180714175936W2skjmQcdXgGDy58.gif", "praise_count": 0, "perfect": 0, "select": 0}, {"id": 292625, "content": "推送太频繁，看着烦", "image": "img/option/option/20180714175825ywU9qZMdhKgQI1Ef.gif", "praise_count": 0, "perfect": 0, "select": 0}, {"id": 292626, "content": "因为某个兴趣关注的，但之后再没看到啥有意思的东西", "image": "img/option/option/20180714175920Qr58FlsyP6p1JbNm.gif", "praise_count": 0, "perfect": 0, "select": 0}, {"id": 292627, "content": "内容风格跟其他账号重复，在PK中不幸落选", "image": "img/option/option/20180714180000UMQGs3zqObHm7EuD.gif", "praise_count": 0, "perfect": 0, "select": 0}, {"id": 292629, "content": "为了工作关注的，离职/转行就取关了", "image": "img/option/option/20180714180734CIw0X7fbcF3n2jU5.gif", "praise_count": 0, "perfect": 0, "select": 0}]}]}