{"id": 362, "genre": 1000, "title": "你为什么用Kindle？", "description": "无论看书还是装X，性价比都高。\r\n", "record_count": 3259, "comment_count": 47, "praise_count": 0, "image": "img/paper/paper_show/201607031813502f5Muo9eWs6Ppwtk.jpg", "page_style": 0, "category": 1, "column": 2, "type": "paper", "date": "2015-05-12T08:13:54Z", "questions": [{"id": 256, "title": "你为什么用Kindle？", "content": "你为什么用Kindle？\r\n", "genre": 1, "options": [{"id": 2234, "content": "为了不眼瞎瞎", "image": "img/option/option/20160607192917YRAbjKrkEHxVwpNq.jpg", "praise_count": 0, "perfect": 0, "select": 0}, {"id": 2235, "content": "为了不买占地方的纸质书", "image": "img/option/option/20160607193155UGW8VC1SspQbJi35.jpg", "praise_count": 0, "perfect": 0, "select": 0}, {"id": 2236, "content": "我并不留恋纸书", "image": "img/option/option/20160607192918UiKaw5TY0ytRLBqD.jpg", "praise_count": 0, "perfect": 0, "select": 0}, {"id": 2237, "content": "方便做笔记", "image": "img/option/option/20160607192918h4YEpFa1VNoi8OBn.jpg", "praise_count": 0, "perfect": 0, "select": 0}, {"id": 2238, "content": "为了把网页存起来", "image": "img/option/option/20160607192918J8wydAICNcHBmlzX.gif", "praise_count": 0, "perfect": 0, "select": 0}, {"id": 2239, "content": "电子书便宜", "image": "img/option/option/20160607193928NS20RTWgLAeJ76vV.gif", "praise_count": 0, "perfect": 0, "select": 0}, {"id": 2240, "content": "为督促自己看书找个理由", "image": "img/option/option/20160607192918ISp9Y0Xeo6CKAk8b.jpg", "praise_count": 0, "perfect": 0, "select": 0}, {"id": 2241, "content": "有B格，还便宜", "image": "img/option/option/20160702182655YdvhIDgakepjMmC7.jpg", "praise_count": 0, "perfect": 0, "select": 0}, {"id": 2242, "content": "配件好看", "image": "img/option/option/20160607192918uslI2MwVPp9Xcd7o.jpg", "praise_count": 0, "perfect": 0, "select": 0}, {"id": 2243, "content": "对我这种有钱人来说，看见这价格就想买", "image": "img/option/option/20160702182550qCK4WNsmHJQSO56n.gif", "praise_count": 0, "perfect": 0, "select": 0}, {"id": 2244, "content": "我不用kindle", "image": "img/option/option/20160703181316v51TICmlftzLZ9Od.jpeg", "praise_count": 0, "perfect": 0, "select": 0}]}]}