{"id": 931, "genre": 1000, "title": "你觉得现代人“复古病”的临床表现有哪些？", "description": "抵制一切现代科技，视之为人类的异化和堕落的根源，即使是电磁炉都不能例外。（题图来自：林小妖）", "record_count": 2952, "comment_count": 27, "praise_count": 0, "image": "img/paper/paper_show/20160702183700Yo4GXWphHKyIc7PA.jpg", "page_style": 0, "category": 1, "column": 2, "type": "paper", "date": "2016-04-12T01:01:12Z", "questions": [{"id": 815, "title": "你觉得现代人“复古病”的临床表现有哪些？", "content": "你觉得现代人“复古病”的临床表现有哪些？", "genre": 2, "options": [{"id": 65439, "content": "出高价购买留有霉味的vintage古着", "image": "img/option/option/20160702182713t2kVCzuWHpAm9LDB.gif", "praise_count": 0, "perfect": 0, "select": 0}, {"id": 65440, "content": "喝水要用搪瓷杯，杯口掉瓷的那种为最佳", "image": "img/option/option/201607021829403XwohtryR7PAkmuH.gif", "praise_count": 0, "perfect": 0, "select": 0}, {"id": 65441, "content": "一直唠叨着“想用非智能手机”", "image": "img/option/option/20160702182940coyHUs8V2aYXv916.gif", "praise_count": 0, "perfect": 0, "select": 0}, {"id": 65443, "content": "用繁体字交流，但并不会书写", "image": "img/option/option/20160702182941ERwbCfo7aKZHrgch.gif", "praise_count": 0, "perfect": 0, "select": 0}, {"id": 65445, "content": "不分场合地滥用“从前慢”", "image": "img/option/option/201607021829416dNiUBL2KDeCc1qw.gif", "praise_count": 0, "perfect": 0, "select": 0}, {"id": 65448, "content": "永远在言语中表达对上世纪的一种执念", "image": "img/option/option/20160702182941ir4xh6AEIyjfz0uc.gif", "praise_count": 0, "perfect": 0, "select": 0}, {"id": 65450, "content": "即使是小户型也要购买大件中古家具", "image": "img/option/option/20160702182648GS24ch96px1dYtkj.gif", "praise_count": 0, "perfect": 0, "select": 0}]}]}